qualtran/__init__.py
qualtran/_version.py
qualtran/conftest.py
qualtran/testing.py
qualtran/testing_test.py
qualtran/_infra/__init__.py
qualtran/_infra/adjoint.py
qualtran/_infra/adjoint_test.py
qualtran/_infra/binst_graph_iterators.py
qualtran/_infra/binst_graph_iterators_test.py
qualtran/_infra/bloq.py
qualtran/_infra/bloq_example.py
qualtran/_infra/bloq_example_test.py
qualtran/_infra/bloq_test.py
qualtran/_infra/composite_bloq.py
qualtran/_infra/composite_bloq_test.py
qualtran/_infra/controlled.py
qualtran/_infra/controlled_test.py
qualtran/_infra/data_types.py
qualtran/_infra/data_types_test.py
qualtran/_infra/gate_with_registers.py
qualtran/_infra/gate_with_registers_test.py
qualtran/_infra/quantum_graph.py
qualtran/_infra/quantum_graph_test.py
qualtran/_infra/registers.py
qualtran/_infra/registers_test.py
qualtran/bloqs/__init__.py
qualtran/bloqs/arithmetic/__init__.py
qualtran/bloqs/arithmetic/_shims.py
qualtran/bloqs/arithmetic/addition.py
qualtran/bloqs/arithmetic/addition_test.py
qualtran/bloqs/arithmetic/bitwise.py
qualtran/bloqs/arithmetic/bitwise_test.py
qualtran/bloqs/arithmetic/comparison.py
qualtran/bloqs/arithmetic/comparison_test.py
qualtran/bloqs/arithmetic/controlled_add_or_subtract.py
qualtran/bloqs/arithmetic/controlled_add_or_subtract_test.py
qualtran/bloqs/arithmetic/controlled_addition.py
qualtran/bloqs/arithmetic/controlled_addition_test.py
qualtran/bloqs/arithmetic/hamming_weight.py
qualtran/bloqs/arithmetic/hamming_weight_test.py
qualtran/bloqs/arithmetic/multiplication.py
qualtran/bloqs/arithmetic/multiplication_test.py
qualtran/bloqs/arithmetic/negate.py
qualtran/bloqs/arithmetic/negate_test.py
qualtran/bloqs/arithmetic/permutation.py
qualtran/bloqs/arithmetic/permutation_test.py
qualtran/bloqs/arithmetic/sorting.py
qualtran/bloqs/arithmetic/sorting_test.py
qualtran/bloqs/arithmetic/subtraction.py
qualtran/bloqs/arithmetic/subtraction_test.py
qualtran/bloqs/arithmetic/conversions/__init__.py
qualtran-0.6.1.dist-info/licenses/LICENSE
qualtran-0.6.1.dist-info/METADATA
qualtran-0.6.1.dist-info/WHEEL
qualtran-0.6.1.dist-info/top_level.txt
qualtran-0.6.1.dist-info/RECORD
