Metadata-Version: 2.4
Name: qualtran
Version: 0.6.1
Summary: Software for fault-tolerant quantum algorithms research.
Author: Google Quantum AI
Author-email: mpharrigan@google.com
License: Apache 2
License-File: LICENSE
Requires-Dist: attrs>=23.2.0
Requires-Dist: cachetools>=5.3
Requires-Dist: networkx
Requires-Dist: numpy
Requires-Dist: sympy
Requires-Dist: cirq-core==1.4
Requires-Dist: fxpmath
Requires-Dist: galois
Requires-Dist: nbconvert
Requires-Dist: nbformat
Requires-Dist: notebook
Requires-Dist: pydot
Requires-Dist: ipython
Requires-Dist: matplotlib
Requires-Dist: ipywidgets
Requires-Dist: plotly
Requires-Dist: dash
Requires-Dist: quimb
Requires-Dist: qsharp
Requires-Dist: qsharp-widgets
Requires-Dist: qref==0.9.0
Requires-Dist: bartiq==0.9.0
Requires-Dist: pyzx
Requires-Dist: pennylane
Requires-Dist: protobuf
Requires-Dist: typing_extensions>=4.10.0
Dynamic: author
Dynamic: author-email
Dynamic: description
Dynamic: description-content-type
Dynamic: license
Dynamic: license-file
Dynamic: requires-dist
Dynamic: summary
